__init__.py
beaverpy/Conv2D.py
beaverpy/CosineSimilarity.py
beaverpy/Linear.py
beaverpy/MSELoss.py
beaverpy/MaxPool2D.py
beaverpy/ReLU.py
beaverpy/Sigmoid.py
beaverpy/Softmax.py
beaverpy/__init__.py
beaverpy-0.1.0.dist-info/LICENSE
beaverpy-0.1.0.dist-info/METADATA
beaverpy-0.1.0.dist-info/WHEEL
beaverpy-0.1.0.dist-info/top_level.txt
beaverpy-0.1.0.dist-info/RECORD
