Metadata-Version: 2.1
Name: beaverpy
Version: 0.1.0
Summary: `beaverpy` is an implementation of PyTorch operators using only NumPy
Author-email: Sai Anuroop Kesanapalli <ksanu1998@gmail.com>
Project-URL: Homepage, https://github.com/ksanu1998/beaverpy
Project-URL: Bug Tracker, https://github.com/ksanu1998/beaverpy/issues
Classifier: Programming Language :: Python :: 3
Classifier: License :: OSI Approved :: MIT License
Classifier: Operating System :: OS Independent
Requires-Python: >=3.7
License-File: LICENSE
